testcode/check_dihedrals.ipynb
testcode/dihedral_parsing_numpy.ipynb
testcode/test_argparse.py
repex_topology_parser-0.2.2.dist-info/METADATA
repex_topology_parser-0.2.2.dist-info/WHEEL
repex_topology_parser-0.2.2.dist-info/top_level.txt
repex_topology_parser-0.2.2.dist-info/RECORD
