Metadata-Version: 2.4
Name: repex_topology_parser
Version: 0.2.2
Author-email: Korey M Reid <r.korey@pm.me>, Tzu-Ping Chung <tzu-ping@example.com>
Maintainer-email: Korey M Reid <r.korey@pm.me>
License-Expression: GPL-3.0-or-later
Project-URL: Homepage, https://github.com/koreyr/repex_topology_parser/
Project-URL: Documentation, https://github.com/koreyr/repex_topology_parser/README.md
Project-URL: Repository, https://github.com/koreyr/repex_topology_parser.git
Project-URL: Issues, https://github.com/koreyr/repex_topology_parser/issues
Classifier: Development Status :: 4 - Beta
Classifier: Intended Audience :: Science/Research
Classifier: Topic :: Scientific/Engineering :: Chemistry
Classifier: Programming Language :: Python :: 3
Classifier: Programming Language :: Python :: 3.8
Classifier: Programming Language :: Python :: 3.9
Classifier: Programming Language :: Python :: 3.10
Classifier: Programming Language :: Python :: 3.11
Requires-Python: >=3.9
Requires-Dist: numpy>=1.26.4
